ofunctions.service_control-1.0.0-py3.8-nspkg.pth
ofunctions/service_control/__init__.py
ofunctions.service_control-1.0.0.dist-info/LICENSE
ofunctions.service_control-1.0.0.dist-info/METADATA
ofunctions.service_control-1.0.0.dist-info/WHEEL
ofunctions.service_control-1.0.0.dist-info/namespace_packages.txt
ofunctions.service_control-1.0.0.dist-info/top_level.txt
ofunctions.service_control-1.0.0.dist-info/RECORD
